{
  "project_info": {
    "project_number": "549806300892",
    "project_id": "comity-abd6b",
    "storage_bucket": "comity-abd6b.appspot.com"
  },
  "client": [
    {
      "client_info": {
        "mobilesdk_app_id": "1:549806300892:android:60a20fe8cf6e55a6d4de19",
        "android_client_info": {
          "package_name": "com.example.comity"
        }
      },
      "oauth_client": [
        {
          "client_id": "549806300892-k8c5orf4inr55m27q8ac4k1rbbrbt5q1.apps.googleusercontent.com",
          "client_type": 3
        }
      ],
      "api_key": [
        {
          "current_key": "AIzaSyAUusYzOW249DdepneEuYZWxSCJxUeXP0w"
        }
      ],
      "services": {
        "appinvite_service": {
          "other_platform_oauth_client": [
            {
              "client_id": "549806300892-k8c5orf4inr55m27q8ac4k1rbbrbt5q1.apps.googleusercontent.com",
              "client_type": 3
            }
          ]
        }
      }
    }
  ],
  "configuration_version": "1"
}